osafe/__init__.py
osafe/__main__.py
osafe/cli.py
osafe/config.py
osafe/editor.py
osafe/utils.py
osafe/encryption/__init__.py
osafe/encryption/content.py
osafe/encryption/encryption.py
osafe/encryption/key.py
osafe/encryption/message.py
osafe/storage/__init__.py
osafe/storage/drive_storage_format.py
osafe/storage/storage.py
osafe/storage/storage_format.py
osafe-1.0.0.dist-info/LICENSE
osafe-1.0.0.dist-info/METADATA
osafe-1.0.0.dist-info/WHEEL
osafe-1.0.0.dist-info/entry_points.txt
osafe-1.0.0.dist-info/top_level.txt
osafe-1.0.0.dist-info/RECORD
