Metadata-Version: 2.1
Name: osafe
Version: 1.0.0
Summary: A Python implementation of OSafe.
Home-page: https://github.com/osafe/osafe-python
Author: Oded Niv
Author-email: oded.niv@gmail.com
License: MIT
Platform: UNKNOWN
Classifier: Programming Language :: Python
Classifier: Programming Language :: Python :: 3.6
Classifier: License :: OSI Approved :: MIT License
Classifier: Operating System :: OS Independent
Requires-Dist: cached-property
Requires-Dist: pycrypto
Requires-Dist: google-api-python-client
Requires-Dist: oauth2client
Requires-Dist: click
